rustafarian-0.4.0.dist-info/METADATA
rustafarian-0.4.0.dist-info/WHEEL
rustafarian-0.4.0.dist-info/entry_points.txt
rustafarian/module/double.py
rustafarian/module/__init__.py
rustafarian/cli.py
rustafarian/__init__.py
rustafarian/rustafarian.cpython-37m-x86_64-linux-gnu.so
rustafarian-0.4.0.dist-info/RECORD
