Metadata-Version: 2.1
Name: rustafarian
Version: 0.4.0
Classifier: Programming Language :: Python
Requires-Dist: click>=7.0
Author: Roberto Di Remigio <roberto.diremigio@gmail.com>
Author-Email: Roberto Di Remigio <roberto.diremigio@gmail.com>
Requires-Python: >=3.6
